stm_sim/__init__.py
stm_sim/stm.py
stm_sim-0.3.4.dist-info/licenses/LICENSE
stm_sim-0.3.4.dist-info/METADATA
stm_sim-0.3.4.dist-info/WHEEL
stm_sim-0.3.4.dist-info/top_level.txt
stm_sim-0.3.4.dist-info/RECORD
