Metadata-Version: 2.4
Name: stm_sim
Version: 0.3.4
Summary: An STM simulation python library.
Home-page: https://gitee.com/pjren/stm_sim
Author: Renpj
Author-email: 0403114076@163.com
License: MIT
Classifier: Programming Language :: Python :: 3
Classifier: Operating System :: OS Independent
License-File: LICENSE
Requires-Dist: ase
Requires-Dist: surface_construct
Dynamic: author
Dynamic: author-email
Dynamic: classifier
Dynamic: description
Dynamic: description-content-type
Dynamic: home-page
Dynamic: license
Dynamic: license-file
Dynamic: requires-dist
Dynamic: summary
